tth/__init__.py
tth/api/__init__.py
tth/api/artifact.py
tth/api/execution.py
tth/api/report.py
tth/api/trigger.py
tth/client/__init__.py
tth/client/api_key_client.py
tth/client/client_base.py
tth/data/__init__.py
tth/data/record.py
tth/uploader/__init__.py
tth/uploader/constants.py
tth/uploader/manual_uploader.py
tth/uploader/plugin.py
tth/uploader/report_handler.py
tth/uploader/settings.py
tth/uploader/utils.py
tth/utils/__init__.py
tth/utils/exception.py
tth-upload/__init__.py
tth-upload/__main__.py
tth_api_client-1.4.0.dist-info/METADATA
tth_api_client-1.4.0.dist-info/WHEEL
tth_api_client-1.4.0.dist-info/entry_points.txt
tth_api_client-1.4.0.dist-info/top_level.txt
tth_api_client-1.4.0.dist-info/RECORD
