Metadata-Version: 2.1
Name: tth-api-client
Version: 1.4.0
Summary: Typhoon Test Hub API client library
Home-page: https://github.com/typhoon-hil
Author: Typhoon HIL
Author-email: vanja.mijatov@typhoon-hil.com
Classifier: Framework :: Pytest
Classifier: Development Status :: 5 - Production/Stable
Classifier: Intended Audience :: Developers
Classifier: License :: Other/Proprietary License
Classifier: Operating System :: MacOS :: MacOS X
Classifier: Operating System :: Microsoft :: Windows
Classifier: Operating System :: POSIX
Classifier: Programming Language :: Python :: 3
Classifier: Programming Language :: Python :: 3 :: Only
Classifier: Programming Language :: Python :: 3.8
Classifier: Programming Language :: Python :: 3.9
Classifier: Programming Language :: Python :: 3.10
Classifier: Programming Language :: Python :: 3.11
Classifier: Programming Language :: Python :: 3.12
Classifier: Programming Language :: Python :: 3.13
Classifier: Programming Language :: Python :: 3.14
Classifier: Topic :: Software Development :: Libraries
Classifier: Topic :: Software Development :: Testing
Classifier: Topic :: Utilities
Requires-Python: >=3.8,<3.15
Requires-Dist: allure-pytest
Requires-Dist: requests >=2.28.0
Requires-Dist: requests-toolbelt >=1.0.0
